[{"link": "https://careerbuilder.vn/vi/tim-viec-lam/java-developer.35BF2D88.html", "vi_tri_viec": "Java Developer", "ten_cong_ty": "C\u00d4NG TY TNHH BTM GLOBAL CONSULTING VI\u1ec6T NAM", "company_link": "https://careerbuilder.vn/vi/nha-tuyen-dung/cong-ty-tnhh-btm-global-consulting-viet-nam.35A98E89.html", "\u0110\u1ecba \u0111i\u1ec3m": "H\u1ed3 Ch\u00ed Minh", "Ng\u00e0y c\u1eadp nh\u1eadt": "12/12/2023", "Ng\u00e0nh ngh\u1ec1": "CNTT - Ph\u1ea7n m\u1ec1m", "H\u00ecnh th\u1ee9c": "Nh\u00e2n vi\u00ean ch\u00ednh th\u1ee9c", "L\u01b0\u01a1ng": "8 Tr - 18 Tr VND", "Kinh nghi\u1ec7m": "Tr\u00ean 1 N\u0103m", "C\u1ea5p b\u1eadc": "Nh\u00e2n vi\u00ean", "H\u1ebft h\u1ea1n n\u1ed9p": "12/01/2024", "company_info": "\u0110\u1ecba \u0111i\u1ec3mT\u1ea7ng 2, T\u00f2a nh\u00e0 HELIOS, \u0110\u01b0\u1eddng s\u1ed1 3, C\u00f4ng vi\u00ean ph\u1ea7n m\u1ec1m Quang Trung, Ph\u01b0\u1eddng T\u00e2n Ch\u00e1nh Hi\u1ec7p, Qu\u1eadn 12, Th\u00e0nh ph\u1ed1 H\u1ed3 Ch\u00ed Minh, Vi\u1ec7t Nam\nTh\u00f4ng tin c\u00f4ng ty\nNg\u01b0\u1eddi li\u00ean h\u1ec7: Ngan Nguyen\nLo\u1ea1i h\u00ecnh ho\u1ea1t \u0111\u1ed9ng: Tr\u00e1ch nhi\u1ec7m h\u1eefu h\u1ea1n\nWebsite: https://btmglobal.com.vn/\n100 followers", "company_follower_number": "100", "error": false}, {"link": "https://careerbuilder.vn/vi/tim-viec-lam/lap-trinh-vien-mobile.35BF2D86.html", "vi_tri_viec": "L\u1eadp tr\u00ecnh vi\u00ean Mobile", "ten_cong_ty": "Phu Hung Securities Corporation", "company_link": "https://careerbuilder.vn/vi/nha-tuyen-dung/phu-hung-securities-corporation.35A80027.html", "\u0110\u1ecba \u0111i\u1ec3m": "H\u1ed3 Ch\u00ed Minh", "Ng\u00e0y c\u1eadp nh\u1eadt": "12/12/2023", "Ng\u00e0nh ngh\u1ec1": "Ch\u1ee9ng kho\u00e1n , CNTT - Ph\u1ea7n m\u1ec1m", "H\u00ecnh th\u1ee9c": "Nh\u00e2n vi\u00ean ch\u00ednh th\u1ee9c", "L\u01b0\u01a1ng": "C\u1ea1nh tranh", "Kinh nghi\u1ec7m": "2 - 3 N\u0103m", "C\u1ea5p b\u1eadc": "Nh\u00e2n vi\u00ean", "H\u1ebft h\u1ea1n n\u1ed9p": "31/01/2024", "company_info": "\u0110\u1ecba \u0111i\u1ec3mT\u1ea7ng 21, Ph\u00fa M\u1ef9 H\u01b0ng Tower, 08 Ho\u00e0ng V\u0103n Th\u00e1i, Ph\u01b0\u1eddng T\u00e2n Ph\u00fa, Qu\u1eadn 7, TP. HCM\nTh\u00f4ng tin c\u00f4ng ty\nNg\u01b0\u1eddi li\u00ean h\u1ec7: Ms. Th\u01a1 Nguy\u1ec5n\nQui m\u00f4 c\u00f4ng ty: 100-499\nLo\u1ea1i h\u00ecnh ho\u1ea1t \u0111\u1ed9ng: C\u1ed5 ph\u1ea7n\nWebsite: https://talent.phs.vn/\n715 followers", "company_follower_number": "715", "error": false}, {"link": "https://careerbuilder.vn/vi/tim-viec-lam/giam-sat-kinh-doanh-kenh-sieu-thi-mang-planning.35BF2D7B.html", "vi_tri_viec": "Gi\u00e1m S\u00e1t Kinh Doanh - K\u00eanh Si\u00eau Th\u1ecb (M\u1ea3ng Planning)", "ten_cong_ty": "C\u00f4ng Ty C\u1ed5 Ph\u1ea7n Goody Group", "company_link": "https://careerbuilder.vn/vi/nha-tuyen-dung/cong-ty-co-phan-goody-group.35A8438E.html", "\u0110\u1ecba \u0111i\u1ec3m": "H\u1ed3 Ch\u00ed Minh", "Ng\u00e0y c\u1eadp nh\u1eadt": "12/12/2023", "Ng\u00e0nh ngh\u1ec1": "Th\u1ef1c ph\u1ea9m & \u0110\u1ed3 u\u1ed1ng , B\u00e1n h\u00e0ng / Kinh doanh , B\u00e1n l\u1ebb / B\u00e1n s\u1ec9", "H\u00ecnh th\u1ee9c": "Nh\u00e2n vi\u00ean ch\u00ednh th\u1ee9c", "L\u01b0\u01a1ng": "C\u1ea1nh tranh", "Kinh nghi\u1ec7m": "4 - 6 N\u0103m", "C\u1ea5p b\u1eadc": "Tr\u01b0\u1edfng nh\u00f3m / Gi\u00e1m s\u00e1t", "H\u1ebft h\u1ea1n n\u1ed9p": "31/12/2023", "company_info": "\u0110\u1ecba \u0111i\u1ec3m139 Pasteur, Ph\u01b0\u1eddng V\u00f5 Th\u1ecb S\u00e1u, Qu\u1eadn 3, Tp. HCM\nTh\u00f4ng tin c\u00f4ng ty\nNg\u01b0\u1eddi li\u00ean h\u1ec7: HR Dept\nQui m\u00f4 c\u00f4ng ty: 100-499\nLo\u1ea1i h\u00ecnh ho\u1ea1t \u0111\u1ed9ng: C\u1ed5 ph\u1ea7n\nWebsite: http://starkombucha.com\n5.739 followers", "company_follower_number": "5.739", "error": false}, {"link": "https://careerbuilder.vn/vi/tim-viec-lam/chuyen-vien-dieu-phoi-du-an-project-coordinator.35BF2D83.html", "vi_tri_viec": "Chuy\u00ean vi\u00ean \u0111i\u1ec1u ph\u1ed1i d\u1ef1 \u00e1n (Project Coordinator)", "ten_cong_ty": "PTSC Offshore Services (POS)", "company_link": "https://careerbuilder.vn/vi/nha-tuyen-dung/ptsc-offshore-services-pos.35A59C56.html", "\u0110\u1ecba \u0111i\u1ec3m": "B\u00e0 R\u1ecba - V\u0169ng T\u00e0u", "Ng\u00e0y c\u1eadp nh\u1eadt": "12/12/2023", "Ng\u00e0nh ngh\u1ec1": "H\u00e0ng h\u1ea3i , D\u1ea7u kh\u00ed , S\u1ea3n xu\u1ea5t / V\u1eadn h\u00e0nh s\u1ea3n xu\u1ea5t", "H\u00ecnh th\u1ee9c": "Nh\u00e2n vi\u00ean ch\u00ednh th\u1ee9c", "L\u01b0\u01a1ng": "C\u1ea1nh tranh", "Kinh nghi\u1ec7m": "2 - 15 N\u0103m", "C\u1ea5p b\u1eadc": "Nh\u00e2n vi\u00ean", "H\u1ebft h\u1ea1n n\u1ed9p": "12/01/2024", "company_info": "\u0110\u1ecba \u0111i\u1ec3mC\u1ea3ng H\u1ea1 L\u01b0u PTSC, 65A \u0111\u01b0\u1eddng 30/04, P. Th\u1eafng Nh\u1ea5t, TP. V\u0169ng T\u00e0u\nTh\u00f4ng tin c\u00f4ng ty\nNg\u01b0\u1eddi li\u00ean h\u1ec7: Tuyen Dung POS\nQui m\u00f4 c\u00f4ng ty: 500-999\nLo\u1ea1i h\u00ecnh ho\u1ea1t \u0111\u1ed9ng: Tr\u00e1ch nhi\u1ec7m h\u1eefu h\u1ea1n\nWebsite: http://pos.ptsc.com.vn/\n508 followers", "company_follower_number": "508", "error": false}, {"link": "https://careerbuilder.vn/vi/tim-viec-lam/thu-ky-tieng-han-korean-speaking.35BF2D81.html", "vi_tri_viec": "TH\u01af K\u00dd TI\u1ebeNG H\u00c0N (KOREAN SPEAKING)", "ten_cong_ty": "Samsung Electronics HCMC CE Complex Co., Ltd", "company_link": "https://careerbuilder.vn/vi/nha-tuyen-dung/samsung-electronics-hcmc-ce-complex-co-ltd.35A4EE25.html", "\u0110\u1ecba \u0111i\u1ec3m": "H\u1ed3 Ch\u00ed Minh", "Ng\u00e0y c\u1eadp nh\u1eadt": "12/12/2023", "Ng\u00e0nh ngh\u1ec1": "H\u00e0nh ch\u00ednh / Th\u01b0 k\u00fd , Ng\u00e0nh kh\u00e1c", "H\u00ecnh th\u1ee9c": "Nh\u00e2n vi\u00ean ch\u00ednh th\u1ee9c", "L\u01b0\u01a1ng": "C\u1ea1nh tranh", "C\u1ea5p b\u1eadc": "Nh\u00e2n vi\u00ean", "H\u1ebft h\u1ea1n n\u1ed9p": "12/01/2024", "company_info": "\u0110\u1ecba \u0111i\u1ec3mSamsung Electronics HCMC CE Complex\nTh\u00f4ng tin c\u00f4ng ty\nNg\u01b0\u1eddi li\u00ean h\u1ec7: Recruitment Team\nQui m\u00f4 c\u00f4ng ty: 6000 - 10000\nLo\u1ea1i h\u00ecnh ho\u1ea1t \u0111\u1ed9ng: 100% v\u1ed1n n\u01b0\u1edbc ngo\u00e0i\nWebsite: https://www.facebook.com/recruitment.sehc/\n5.861 followers", "company_follower_number": "5.861", "error": false}, {"link": "https://careerbuilder.vn/vi/tim-viec-lam/ky-su-thiet-ke-tokyo-nhat-ban-tu-6-thang-kinh-nghiem-tieng-nhat-n3-25-55-man.35BF2D84.html", "vi_tri_viec": "K\u1ef8 S\u01af THI\u1ebeT K\u1ebe - TOKYO, NH\u1eacT B\u1ea2N - T\u1eea 6 TH\u00c1NG KINH NGHI\u1ec6M, TI\u1ebeNG NH\u1eacT N3 (25-55 man)", "ten_cong_ty": "C\u00f4ng Ty TNHH OS POWER Vi\u1ec7t Nam", "company_link": "https://careerbuilder.vn/vi/nha-tuyen-dung/cong-ty-tnhh-os-power-viet-nam.35A70957.html", "\u0110\u1ecba \u0111i\u1ec3m": "To\u00e0n qu\u1ed1c", "Ng\u00e0y c\u1eadp nh\u1eadt": "12/12/2023", "Ng\u00e0nh ngh\u1ec1": "C\u01a1 kh\u00ed / \u00d4 t\u00f4 / T\u1ef1 \u0111\u1ed9ng h\u00f3a", "H\u00ecnh th\u1ee9c": "Nh\u00e2n vi\u00ean ch\u00ednh th\u1ee9c", "L\u01b0\u01a1ng": "C\u1ea1nh tranh", "Kinh nghi\u1ec7m": "1 - 5 N\u0103m", "C\u1ea5p b\u1eadc": "Nh\u00e2n vi\u00ean", "H\u1ebft h\u1ea1n n\u1ed9p": "31/12/2024", "company_info": "\u0110\u1ecba \u0111i\u1ec3mPh\u00f2ng 12P, T\u1ea7ng 12, Center Building, s\u1ed1 1 nguy\u1ec5n Huy T\u01b0\u1edfng, Thanh Xu\u00e2n, H\u00e0 N\u1ed9i\nTh\u00f4ng tin c\u00f4ng ty\nNg\u01b0\u1eddi li\u00ean h\u1ec7: OSPV\nQui m\u00f4 c\u00f4ng ty: 25-99\nLo\u1ea1i h\u00ecnh ho\u1ea1t \u0111\u1ed9ng: Tr\u00e1ch nhi\u1ec7m h\u1eefu h\u1ea1n\n5.900 followers\nJOIN OUR TALENT NETWORK", "company_follower_number": "5.900", "error": false}, {"link": "https://careerbuilder.vn/vi/tim-viec-lam/chuyen-vien-khach-hang-ca-nhan.35BF2D7F.html", "vi_tri_viec": "Chuy\u00ean vi\u00ean Kh\u00e1ch h\u00e0ng c\u00e1 nh\u00e2n", "ten_cong_ty": "Ng\u00e2n H\u00e0ng TMCP X\u0103ng D\u1ea7u Petrolimex (PG Bank)", "company_link": "https://careerbuilder.vn/vi/nha-tuyen-dung/ngan-hang-tmcp-xang-dau-petrolimex-pg-bank.35A6D6F6.html", "\u0110\u1ecba \u0111i\u1ec3m": "Thanh H\u00f3a", "Ng\u00e0y c\u1eadp nh\u1eadt": "12/12/2023", "Ng\u00e0nh ngh\u1ec1": "B\u00e1n h\u00e0ng / Kinh doanh , Ng\u00e2n h\u00e0ng , B\u1ea3o hi\u1ec3m", "H\u00ecnh th\u1ee9c": "Nh\u00e2n vi\u00ean ch\u00ednh th\u1ee9c", "L\u01b0\u01a1ng": "10 Tr - 30 Tr VND", "Kinh nghi\u1ec7m": "1 - 3 N\u0103m", "C\u1ea5p b\u1eadc": "Nh\u00e2n vi\u00ean", "H\u1ebft h\u1ea1n n\u1ed9p": "07/01/2024", "company_info": "\u0110\u1ecba \u0111i\u1ec3mT\u1ea7ng 24, T\u00f2a th\u00e1p v\u0103n ph\u00f2ng Mipec, 229 T\u00e2y S\u01a1n, \u0110\u1ed1ng \u0110a, H\u00e0 N\u1ed9i\nTh\u00f4ng tin c\u00f4ng ty\nNg\u01b0\u1eddi li\u00ean h\u1ec7: PG Bank\nQui m\u00f4 c\u00f4ng ty: 1.000-4.999\nLo\u1ea1i h\u00ecnh ho\u1ea1t \u0111\u1ed9ng: C\u1ed5 ph\u1ea7n\nWebsite: https://www.pgbank.com.vn\n6.134 followers", "company_follower_number": "6.134", "error": false}, {"link": "https://careerbuilder.vn/vi/tim-viec-lam/chuyen-vien-phap-ly.35BF2D7C.html", "vi_tri_viec": "Chuy\u00ean vi\u00ean Ph\u00e1p l\u00fd", "ten_cong_ty": "CHI NH\u00c1NH C\u00d4NG TY TNHH Y T\u1ebe VI\u1ec6T TI\u1ebeN - NH\u00c0 M\u00c1Y S\u1ea2N XU\u1ea4T LONG AN", "company_link": "https://careerbuilder.vn/vi/nha-tuyen-dung/cong-ty-tnhh-y-te-viet-tien.35A964F6.html", "\u0110\u1ecba \u0111i\u1ec3m": "Long An", "Ng\u00e0y c\u1eadp nh\u1eadt": "12/12/2023", "Ng\u00e0nh ngh\u1ec1": "Y t\u1ebf / Ch\u0103m s\u00f3c s\u1ee9c kh\u1ecfe , Lu\u1eadt / Ph\u00e1p l\u00fd", "H\u00ecnh th\u1ee9c": "Nh\u00e2n vi\u00ean ch\u00ednh th\u1ee9c", "L\u01b0\u01a1ng": "C\u1ea1nh tranh", "Kinh nghi\u1ec7m": "Tr\u00ean 1 N\u0103m", "C\u1ea5p b\u1eadc": "Nh\u00e2n vi\u00ean", "H\u1ebft h\u1ea1n n\u1ed9p": "31/01/2024", "company_info": "\u0110\u1ecba \u0111i\u1ec3mS\u1ed1 35-37, \u0111\u01b0\u1eddng s\u1ed1 65, ph\u01b0\u1eddng T\u00e2n Phong, Qu\u1eadn 7\nTh\u00f4ng tin c\u00f4ng ty\nNg\u01b0\u1eddi li\u00ean h\u1ec7: L\u00ea H\u1ea3i Hi\u1ebfu Ki\u00ean\nQui m\u00f4 c\u00f4ng ty: 100-499\nLo\u1ea1i h\u00ecnh ho\u1ea1t \u0111\u1ed9ng: Tr\u00e1ch nhi\u1ec7m h\u1eefu h\u1ea1n\nWebsite: https://www.vthealthcare.vn/\n2.273 followers", "company_follower_number": "2.273", "error": false}, {"link": "https://careerbuilder.vn/vi/tim-viec-lam/chuyen-vien-quan-ly-rui-ro-tin-dung.35BF2D1B.html", "vi_tri_viec": "CHUY\u00caN VI\u00caN QU\u1ea2N L\u00dd R\u1ee6I RO T\u00cdN D\u1ee4NG", "ten_cong_ty": "C\u00d4NG TY TNHH ZOOMLION VI\u1ec6T NAM", "company_link": "https://careerbuilder.vn/vi/nha-tuyen-dung/cong-ty-tnhh-zoomlion-viet-nam.35A7943B.html", "\u0110\u1ecba \u0111i\u1ec3m": "\u0110\u00e0 N\u1eb5ng", "Ng\u00e0y c\u1eadp nh\u1eadt": "12/12/2023", "Ng\u00e0nh ngh\u1ec1": "Ng\u00e2n h\u00e0ng", "H\u00ecnh th\u1ee9c": "Nh\u00e2n vi\u00ean ch\u00ednh th\u1ee9c", "L\u01b0\u01a1ng": "13 Tr - 15 Tr VND", "Kinh nghi\u1ec7m": "3 - 5 N\u0103m", "C\u1ea5p b\u1eadc": "Nh\u00e2n vi\u00ean", "H\u1ebft h\u1ea1n n\u1ed9p": "31/01/2024", "company_info": "\u0110\u1ecba \u0111i\u1ec3mT\u1ea7ng 9, t\u00f2a nh\u00e0 Center Building, s\u1ed1 01 \u0111\u01b0\u1eddng Nguy\u1ec5n Huy T\u01b0\u1edfng, ph\u01b0\u1eddng Thanh Xu\u00e2n Trung, qu\u1eadn Thanh Xu\u00e2n, TP. H\u00e0 N\u1ed9i, Vi\u1ec7t Nam.\nTh\u00f4ng tin c\u00f4ng ty\nNg\u01b0\u1eddi li\u00ean h\u1ec7: Ph\u00f2ng Nh\u00e2n s\u1ef1\nQui m\u00f4 c\u00f4ng ty: 25-99\nLo\u1ea1i h\u00ecnh ho\u1ea1t \u0111\u1ed9ng: 100% v\u1ed1n n\u01b0\u1edbc ngo\u00e0i\nWebsite: https://vn.zoomlion.com/\n675 followers", "company_follower_number": "675", "error": false}, {"link": "https://careerbuilder.vn/vi/tim-viec-lam/quan-ly-salon-kiem-phien-dich-tieng-han-phong-van-nhan-viec-som.35BF2AA0.html", "vi_tri_viec": "Qu\u1ea3n l\u00fd Salon ki\u00eam Phi\u00ean D\u1ecbch Ti\u1ebfng H\u00e0n (Ph\u1ecfng v\u1ea5n nh\u1eadn vi\u1ec7c s\u1edbm)", "ten_cong_ty": "Soyou Beauty Made", "company_link": "https://careerbuilder.vn/vi/nha-tuyen-dung/cong-ty-tnhh-the-win-star.35A97B6E.html", "\u0110\u1ecba \u0111i\u1ec3m": "H\u1ed3 Ch\u00ed Minh", "Ng\u00e0y c\u1eadp nh\u1eadt": "12/12/2023", "Ng\u00e0nh ngh\u1ec1": "Qu\u1ea3n l\u00fd \u0111i\u1ec1u h\u00e0nh", "H\u00ecnh th\u1ee9c": "Nh\u00e2n vi\u00ean ch\u00ednh th\u1ee9c", "L\u01b0\u01a1ng": "20 Tr - 25 Tr VND", "Kinh nghi\u1ec7m": "3 - 5 N\u0103m", "C\u1ea5p b\u1eadc": "Qu\u1ea3n l\u00fd", "H\u1ebft h\u1ea1n n\u1ed9p": "30/12/2023", "error": true}]